CHANGES.txt
README.txt
buildout.cfg
setup.py
src/z3c/__init__.py
src/z3c.davapp.zopeappfile.egg-info/PKG-INFO
src/z3c.davapp.zopeappfile.egg-info/SOURCES.txt
src/z3c.davapp.zopeappfile.egg-info/dependency_links.txt
src/z3c.davapp.zopeappfile.egg-info/namespace_packages.txt
src/z3c.davapp.zopeappfile.egg-info/not-zip-safe
src/z3c.davapp.zopeappfile.egg-info/requires.txt
src/z3c.davapp.zopeappfile.egg-info/top_level.txt
src/z3c/davapp/__init__.py
src/z3c/davapp/zopeappfile/__init__.py
src/z3c/davapp/zopeappfile/configure.zcml
src/z3c/davapp/zopeappfile/ftesting.zcml
src/z3c/davapp/zopeappfile/properties.txt
src/z3c/davapp/zopeappfile/tests.py